stygian/__init__.py
stygian/__main__.py
stygian/device_recorder.py
stygian/dispatcher.py
stygian/radio_manager.py
stygian/version.py
stygian-1.1.3.dist-info/LICENSE.txt
stygian-1.1.3.dist-info/METADATA
stygian-1.1.3.dist-info/WHEEL
stygian-1.1.3.dist-info/entry_points.txt
stygian-1.1.3.dist-info/top_level.txt
stygian-1.1.3.dist-info/RECORD
