Metadata-Version: 2.1
Name: stygian
Version: 1.1.3
Summary: Headless recording program for Asphodel devices
Home-page: https://bitbucket.org/suprocktech/stygian
Author: Suprock Technologies, LLC
Author-email: inquiries@suprocktech.com
License: UNKNOWN
Keywords: asphodel suprock apd
Platform: UNKNOWN
Classifier: Programming Language :: Python :: 3
Classifier: License :: OSI Approved :: ISC License (ISCL)
Classifier: Operating System :: OS Independent
Classifier: Topic :: System :: Hardware
Requires-Python: >=3.6
Requires-Dist: asphodel
Requires-Dist: boto3
Requires-Dist: hyperborea
Requires-Dist: numpy
Requires-Dist: psutil
Requires-Dist: PySide2
Requires-Dist: requests
Requires-Dist: setproctitle
